setup.py
clouddns/__init__.py
clouddns/authentication.py
clouddns/connection.py
clouddns/consts.py
clouddns/domain.py
clouddns/errors.py
clouddns/record.py
clouddns/utils.py
python_clouddns.egg-info/PKG-INFO
python_clouddns.egg-info/SOURCES.txt
python_clouddns.egg-info/dependency_links.txt
python_clouddns.egg-info/not-zip-safe
python_clouddns.egg-info/top_level.txt