Metadata-Version: 1.0
Name: python-clouddns
Version: 0.0.0
Summary: Python interface to Rackspace Cloud DNS 
Home-page: https://github.com/chmouel/python-clouddns
Author: Chmouel Boudjnah
Author-email: chmouel@chmouel.com
License: MIT
Download-URL: https://github.com/chmouel/python-clouddns/zipball/0.0.0
Platform: UNKNOWN
Classifier: Development Status :: 5 - Production/Stable
Classifier: Environment :: Console
Classifier: Intended Audience :: Developers
Classifier: License :: OSI Approved :: MIT License
Classifier: Programming Language :: Python
Classifier: Topic :: Internet :: WWW/HTTP
Classifier: Topic :: Software Development :: Libraries :: Python Modules
Classifier: Topic :: System :: Distributed Computing
Classifier: Topic :: Utilities
